[{
		"service": "Adoption",
		"aol": "Adoption",
		"catchment_type": ["local"],
		"catchment_method": "proximity",
		"link_text": "Adoption",
		"service_url": "https://www.gov.uk/child-adoption/applying-for-an-adoption-court-order",
		"onlineUrl": "",
		"onlineText": ""
	},
	{
		"service": "Bankruptcy",
		"aol": "Bankruptcy",
		"catchment_type": ["local"],
		"catchment_method": "postcode",		
		"link_text": "Bankruptcy",
		"service_url": "https://www.gov.uk/bankruptcy",
		"onlineUrl": "https://www.gov.uk/apply-for-bankruptcy",
		"onlineText": ""
	},
	{
		"service": "Benefits",
		"aol": "Social security",
		"catchment_type": ["local","national"],
		"catchment_method": "proximity",
		"link_text": "Benefits",
		"service_url": "https://www.gov.uk/appeal-benefit-decision",
		"onlineUrl": "https://www.gov.uk/appeal-benefit-decision/submit-appeal",
		"onlineText": "Appeal a benefits decision online",
		"SCstatement1": "We manage benefit appeals at our central service centre.",
		"SCstatement2": "Find where to send your documents or ask about your application’s progress."
	},
	{
		"service": "Child arrangements",
		"aol": "Children",
		"catchment_type": ["local"],
		"catchment_method": "local authority",
		"link_text": "Childcare arrangements if you separate from your partner",
		"service_url": "https://www.gov.uk/looking-after-children-divorce",
		"onlineUrl": "https://apply-to-court-about-child-arrangements.service.justice.gov.uk/",
		"onlineText": ""
	},
	{
		"service": "Civil partnership",
		"aol": "Civil partnership",
		"catchment_type": ["regional","national"],
		"catchment_method": "local authority",
		"link_text": "Civil partnership",
		"service_url": "https://www.gov.uk/end-civil-partnership",
		"onlineUrl": "",
		"onlineText": "",
		"SCstatement1": "We manage applications to dissolve a civil partnership at our central service centre.",
		"SCstatement2": "Find where to send your documents or ask about your application’s progress.",
		"SCstatement3": "We manage applications to dissolve a civil partnership at our regional divorce units (RDU). This is the nearest RDU to "
	},
	{
		"service": "Claims against employers",
		"aol": "Employment",
		"catchment_type": ["local"],
		"catchment_method": "proximity",
		"link_text": "Claims against employers",
		"service_url": "https://www.gov.uk/employment-tribunals",
		"onlineUrl": "",
		"onlineText": ""
	},
	{
		"service": "Major criminal offences",
		"aol": "Crime",
		"catchment_type": ["local","national"],
		"catchment_method": "proximity",
		"link_text": "Crime",
		"service_url": "",
		"onlineText": "",
		"SCstatement1": "We manage major criminal offences at our central service centre.",
		"SCstatement2": "Find where to send your documents or ask about your case."
	},
	{
		"service": "Minor criminal offences",
		"aol" : "Minor crime",
		"catchment_type": ["local","national"],
		"catchment_method": "proximity",
		"link_text": "Minor crime",
		"service_url": "",
		"onlineText": "",
		"SCstatement1":"We manage minor criminal offences at our central service centre.",
		"SCstatement2": "Find where to send your documents or ask about your case."
	},
	{
		"service": "Divorce",
		"aol": "Divorce",
		"catchment_type": ["regional","national"],
		"catchment_method": "local authority",
		"link_text": "Divorce",
		"service_url": "https://www.gov.uk/divorce",
		"onlineUrl": "https://www.gov.uk/apply-for-divorce",
		"onlineText": "Apply for a divorce online",
		"SCstatement1": "We manage divorce applications at our central service centre.",
		"SCstatement2": "Find where to send your documents or ask about your application’s progress.",
		"SCstatement3": "We manage divorce applications at our regional divorce units (RDU). This is the nearest RDU to "
	},
	{
		"service": "Domestic abuse",
		"aol":"Domestic violence",
		"catchment_type": ["local"],
		"catchment_method": "proximity",
		"link_text": "Domestic abuse",
		"service_url": "https://www.gov.uk/injunction-domestic-violence",
		"onlineUrl": "",
		"onlineText": ""
	},
	{
		"service": "Forced marriage",
		"aol": "Forced marriage and FGM",
		"catchment_type": ["local"],
		"catchment_method": "proximity",
		"link_text": "Forced marriage",
		"service_url": "https://www.gov.uk/apply-forced-marriage-protection-order",
		"onlineUrl": "",
		"onlineText": ""
	},
	{
		"service": "Female Genital Mutilation",
		"aol": "Forced marriage and FGM",
		"catchment_type": ["local"],
		"catchment_method": "proximity",
		"link_text": "Female Genital Mutilation",
		"service_url": "https://www.gov.uk/government/collections/female-genital-mutilation",
		"onlineUrl": "",
		"onlineText": ""
	},
	{
		"service": "Housing",
		"aol": "Housing possession",
		"catchment_type": ["local"],
		"catchment_method": "postcode",
		"link_text": "Housing",
		"service_url": "https://www.gov.uk/evicting-tenants",
		"onlineUrl": "https://www.gov.uk/possession-claim-online-recover-property",
		"onlineText": "Make or respond to a possession claim online"
	},
	{
		"service": "High Court district registry",
		"aol": "High Court District Registry",
		"catchment_type": ["local"],
		"catchment_method": "proximity",		
		"link_text": "High Court cases – serious or high profile criminal or civil law cases",
		"service_url": "",
		"onlineText": ""
	},
	{
		"service": "Immigration and asylum",
		"aol": "Immigration",
		"catchment_type": ["local","national"],
		"catchment_method": "proximity",
		"link_text": "Immigration and asylum",
		"service_url": "https://www.gov.uk/immigration-asylum-tribunal",
		"onlineUrl": "https://www.gov.uk/immigration-asylum-tribunal",
		"onlineText": "Appeal against a visa or immigration decision",
		"SCstatement1": "We manage your immigration and asylum applications at our central service centre.",
		"SCstatement2": "Find where to send your documents or ask about your application’s progress." 
	},
	{
		"service": "Money claims",
		"aol": "Money claims",
		"catchment_type": ["local","national"],
		"catchment_method": "postcode",
		"link_text": "Money claims",
		"service_url": "https://www.gov.uk/make-court-claim-for-money",
		"onlineUrl": "https://www.gov.uk/make-money-claim",
		"onlineText": "Make a money claim online",
		"SCstatement1": "We manage your money claims applications at our central service centre.",
		"SCstatement2": "Find where to send your documents or ask about your application’s progress." 
	},
	{
		"service": "Probate",
		"aol": "Probate",
		"catchment_type": ["regional","national"],
		"catchment_method": "proximity",		
		"link_text": "Probate",
		"service_url": "https://www.gov.uk/applying-for-probate",
		"onlineUrl": "https://www.gov.uk/applying-for-probate/apply-for-probate",
		"onlineText": "Apply for probate online",
		"SCstatement1": "We manage your probate applications at our central service centre.",
		"SCstatement3": "You can deliver a will or stop a probate application at our regional probate registries. This is the nearest probate registry office to "

	},
	{
		"service": "Tax",
		"aol":"Tax",
		"catchment_type": ["local"],
		"catchment_method": "proximity",
		"link_text": "Tax",
		"service_url": "https://www.gov.uk/tax-tribunal",
		"onlineUrl": ""
	}
]